README.rst
setup.py
brutalelk/__init__.py
brutalelk/brutal_elk_bot.py
brutalelk.egg-info/PKG-INFO
brutalelk.egg-info/SOURCES.txt
brutalelk.egg-info/dependency_links.txt
brutalelk.egg-info/not-zip-safe
brutalelk.egg-info/requires.txt
brutalelk.egg-info/top_level.txt
cmd/elk