Metadata-Version: 1.0
Name: brutalelk
Version: 0.2
Summary: Talk to Brutal Elk and take off your pink sunglasses
Home-page: http://github.com/pannkotsky/brutalelk
Author: Valerii Kovalchuk
Author-email: kovvalole@gmail.com
License: MIT
Platform: UNKNOWN
